iziconf/__init__.py
iziconf/base_settings.py
iziconf/global_settings.py
iziconf/lazy_settings.py
iziconf/utils/__init__.py
iziconf/utils/dict.py
iziconf/utils/functional.py
iziconf/utils/singleton.py
iziconf-0.0.3.dist-info/DESCRIPTION.rst
iziconf-0.0.3.dist-info/METADATA
iziconf-0.0.3.dist-info/RECORD
iziconf-0.0.3.dist-info/WHEEL
iziconf-0.0.3.dist-info/metadata.json
iziconf-0.0.3.dist-info/top_level.txt
