Metadata-Version: 2.0
Name: iziconf
Version: 0.0.3
Summary: iziconf
Home-page: https://github.com/ant31/iziconf
Author: Antoine Legrand
Author-email: 2t.antoine@gmail.com
License: Apache License version 2
Keywords: iziconf
Platform: UNKNOWN
Classifier: Development Status :: 2 - Pre-Alpha
Classifier: Intended Audience :: Developers
Classifier: Natural Language :: English
Classifier: Programming Language :: Python :: 2
Classifier: Programming Language :: Python :: 2.7
Classifier: Programming Language :: Python :: 3.5
Requires-Dist: futures
